[
  {
    "py/object": "model.group.Group",
    "name": "",
    "header": "",
    "footer": "",
    "id": null
  },
  {
    "py/object": "model.group.Group",
    "name": "name-\u043e\u0437A\u0435m\u0438\u044a\u041aC\u042b",
    "header": "header-\u0414\u0427\u041eQW\u0431\u0422\u0448\u0446\u0412A\u0434\u044c\u0444Mt\u0435K\u043c\u0418",
    "footer": "footer-\u0448E\u042e\u042cTTebzl\u0421\u0425\u041dlw",
    "id": null
  },
  {
    "py/object": "model.group.Group",
    "name": "name-\u0431Z\u042b\u0426\u042bH\u043e\u0433\u0426\u0443",
    "header": "header-KU\u0442Xo\u043f\u043emBt3fT\u04467\u041bwF\u041d\u044c",
    "footer": "footer-\u042d\u044avX\u043fb7n\u043f\u0401E5T\u043al",
    "id": null
  },
  {
    "py/object": "model.group.Group",
    "name": "name-mw6W\u0446\u04516\u041bNF",
    "header": "header-9\u0420\u041eq\u0438\u0435\u042f\u043b\u0415\u044c\u0444\u04127ZFF\u04240\u041b2",
    "footer": "footer-\u0444Q\u0419\u0419H2i\u0444Z\u042aY5v\u0441\u042e",
    "id": null
  },
  {
    "py/object": "model.group.Group",
    "name": "name-C\u0423\u0442qB\u042dnL\u042d\u0431",
    "header": "header-\u0425\u0447W\u0446j\u0437\u0431aI\u0415\u0439\u0411o\u0428j3\u0422B\u043d\u042e",
    "footer": "footer-M\u0429Xs\u0436kXZ\u0410MoURd9",
    "id": null
  }
]